seeq/addons/correlation/__init__.py
seeq/addons/correlation/__main__.py
seeq/addons/correlation/_config.py
seeq/addons/correlation/_copy.py
seeq/addons/correlation/_cross_correlations.py
seeq/addons/correlation/_heatmap.py
seeq/addons/correlation/_pairplot.py
seeq/addons/correlation/_preprocessor.py
seeq/addons/correlation/_seeq_add_on.py
seeq/addons/correlation/_seeq_formulas.py
seeq/addons/correlation/_seeq_worksheet_writer.py
seeq/addons/correlation/_version.py
seeq/addons/correlation/deployment_notebook/correlation_analysis_master.ipynb
seeq/addons/correlation/utils/__init__.py
seeq/addons/correlation/utils/_cache_management.py
seeq/addons/correlation/utils/_common.py
seeq/addons/correlation/utils/_permissions.py
seeq/addons/correlation/utils/_sdl.py
seeq/addons/correlation/utils/_seeq_new_content.py
seeq_correlation-0.1.95.dist-info/LICENSE
seeq_correlation-0.1.95.dist-info/METADATA
seeq_correlation-0.1.95.dist-info/NOTICE
seeq_correlation-0.1.95.dist-info/WHEEL
seeq_correlation-0.1.95.dist-info/top_level.txt
seeq_correlation-0.1.95.dist-info/RECORD
