Metadata-Version: 2.1
Name: seeq-correlation
Version: 0.1.95
Summary: Correlation analysis of time series data in Seeq
Home-page: https://github.com/seeq12/seeq-correlation
Author: Seeq Corporation
Author-email: applied.research@seeq.com
License: Apache License 2.0
Platform: Linux
Platform: Windows
Classifier: Programming Language :: Python :: 3.7
Classifier: License :: OSI Approved :: Apache Software License
Classifier: Operating System :: OS Independent
Requires-Python: >=3.7
License-File: LICENSE
License-File: NOTICE
Requires-Dist: dask (>=2021.10.0)
Requires-Dist: ipyvuetify (>=1.5.1)
Requires-Dist: matplotlib (>=3.1.3)
Requires-Dist: memoization (>=0.2.2)
Requires-Dist: numpy (>=1.19.5)
Requires-Dist: pandas (>=1.2.1)
Requires-Dist: pandas (<2.0.0)
Requires-Dist: plotly (>=4.5.0)
Requires-Dist: python-dateutil (>=2.8.1)
Requires-Dist: scikit-learn (>=0.22.1)
Requires-Dist: seaborn (>=0.10.0)
